small_text/__init__.py
small_text/active_learner.py
small_text/base.py
small_text/exceptions.py
small_text/version.json
small_text/version.py
small_text/classifiers/__init__.py
small_text/classifiers/classification.py
small_text/classifiers/factories.py
small_text/data/__init__.py
small_text/data/datasets.py
small_text/data/exceptions.py
small_text/data/sampling.py
small_text/initialization/__init__.py
small_text/initialization/strategies.py
small_text/integrations/__init__.py
small_text/integrations/pytorch/__init__.py
small_text/integrations/pytorch/datasets.py
small_text/integrations/pytorch/exceptions.py
small_text/integrations/pytorch/model_selection.py
small_text/integrations/pytorch/classifiers/__init__.py
small_text/integrations/pytorch/classifiers/base.py
small_text/integrations/pytorch/classifiers/factories.py
small_text/integrations/pytorch/classifiers/kimcnn.py
small_text/integrations/pytorch/models/__init__.py
small_text/integrations/pytorch/models/kimcnn.py
small_text/integrations/pytorch/query_strategies/__init__.py
small_text/integrations/pytorch/query_strategies/strategies.py
small_text/integrations/pytorch/utils/__init__.py
small_text/integrations/pytorch/utils/data.py
small_text/integrations/pytorch/utils/labels.py
small_text/integrations/pytorch/utils/loss.py
small_text/integrations/pytorch/utils/misc.py
small_text/integrations/transformers/__init__.py
small_text/integrations/transformers/datasets.py
small_text/integrations/transformers/classifiers/__init__.py
small_text/integrations/transformers/classifiers/base.py
small_text/integrations/transformers/classifiers/classification.py
small_text/integrations/transformers/classifiers/factories.py
small_text/integrations/transformers/classifiers/setfit.py
small_text/integrations/transformers/utils/__init__.py
small_text/integrations/transformers/utils/classification.py
small_text/integrations/transformers/utils/setfit.py
small_text/query_strategies/__init__.py
small_text/query_strategies/base.py
small_text-1.4.1.dist-info/LICENSE
small_text-1.4.1.dist-info/METADATA
small_text-1.4.1.dist-info/WHEEL
small_text-1.4.1.dist-info/top_level.txt
small_text-1.4.1.dist-info/RECORD
