Metadata-Version: 2.1
Name: small-text
Version: 1.4.1
Summary: Active Learning for Text Classification in Python.
Home-page: https://github.com/webis-de/small-text
Author: Christopher Schröder
Author-email: small-text@protonmail.com
License: MIT License
Keywords: active learning,text classification
Classifier: Development Status :: 5 - Production/Stable
Classifier: License :: OSI Approved :: MIT License
Classifier: Operating System :: OS Independent
Classifier: Programming Language :: Python :: 3
Classifier: Programming Language :: Python :: 3.7
Classifier: Programming Language :: Python :: 3.8
Classifier: Programming Language :: Python :: 3.9
Classifier: Programming Language :: Python :: 3.10
Classifier: Programming Language :: Python :: 3.11
Classifier: Topic :: Scientific/Engineering :: Artificial Intelligence
Classifier: Topic :: Text Processing :: Linguistic
Requires-Python: >=3.7
License-File: LICENSE
Requires-Dist: dill
Requires-Dist: scipy
Requires-Dist: numpy>=1.20.0
Requires-Dist: scikit-learn>=0.24.1
Requires-Dist: tqdm
Requires-Dist: packaging
Provides-Extra: pytorch
Requires-Dist: torch>=1.6.0; extra == "pytorch"
Requires-Dist: torchtext>=0.7.0; extra == "pytorch"
Provides-Extra: transformers
Requires-Dist: torch>=1.6.0; extra == "transformers"
Requires-Dist: torchtext>=0.7.0; extra == "transformers"
Requires-Dist: transformers>=4.0.0; extra == "transformers"
